random_order/__init__.py
random_order/bucket_types.py
random_order/cache.py
random_order/config.py
random_order/plugin.py
random_order/shuffler.py
random_order/xdist.py
pytest_random_order-1.1.1.dist-info/LICENSE
pytest_random_order-1.1.1.dist-info/METADATA
pytest_random_order-1.1.1.dist-info/WHEEL
pytest_random_order-1.1.1.dist-info/entry_points.txt
pytest_random_order-1.1.1.dist-info/top_level.txt
pytest_random_order-1.1.1.dist-info/RECORD
